whatrecord/__init__.py
whatrecord/__main__.py
whatrecord/_version.py
whatrecord/access_security.py
whatrecord/asyn.py
whatrecord/autosave.py
whatrecord/cache.py
whatrecord/client.py
whatrecord/common.py
whatrecord/db.py
whatrecord/dbtemplate.py
whatrecord/format.py
whatrecord/gateway.py
whatrecord/graph.py
whatrecord/graphql.py
whatrecord/gv_compat.py
whatrecord/ioc_finder.py
whatrecord/iocmanager.py
whatrecord/iocsh.py
whatrecord/macro.py
whatrecord/makefile.py
whatrecord/motor.py
whatrecord/parse.py
whatrecord/settings.py
whatrecord/shell.py
whatrecord/snl.py
whatrecord/streamdevice.py
whatrecord/transformer.py
whatrecord/util.py
whatrecord/version.py
whatrecord/bin/__init__.py
whatrecord/bin/deps.py
whatrecord/bin/graph.py
whatrecord/bin/info.py
whatrecord/bin/iocmanager_loader.py
whatrecord/bin/lint.py
whatrecord/bin/main.py
whatrecord/bin/parse.py
whatrecord/bin/server.py
whatrecord/grammar/__init__.py
whatrecord/grammar/access_security.lark
whatrecord/grammar/autosave_save.lark
whatrecord/grammar/db.v3.lark
whatrecord/grammar/db.v4.lark
whatrecord/grammar/dbtemplate.lark
whatrecord/grammar/gateway.lark
whatrecord/grammar/lcls_epicsarch.lark
whatrecord/grammar/msi-sub.lark
whatrecord/grammar/snl.lark
whatrecord/grammar/streamdevice.lark
whatrecord/plugins/__init__.py
whatrecord/plugins/epicsarch.py
whatrecord/plugins/gdb_binary_info.py
whatrecord/plugins/happi.py
whatrecord/plugins/netconfig.py
whatrecord/plugins/twincat_pytmc.py
whatrecord/plugins/util.py
whatrecord/server/__init__.py
whatrecord/server/common.py
whatrecord/server/server.py
whatrecord/server/util.py
whatrecord/tests/__init__.py
whatrecord/tests/access.acf
whatrecord/tests/conftest.py
whatrecord/tests/example.acf
whatrecord/tests/kfe.pvlist
whatrecord/tests/t1-include.txt
whatrecord/tests/test_access.py
whatrecord/tests/test_autosave.py
whatrecord/tests/test_bin_graph.py
whatrecord/tests/test_bin_lint.py
whatrecord/tests/test_bin_parse.py
whatrecord/tests/test_cache.py
whatrecord-0.6.0.dist-info/AUTHORS.rst
whatrecord-0.6.0.dist-info/LICENSE.md
whatrecord-0.6.0.dist-info/METADATA
whatrecord-0.6.0.dist-info/WHEEL
whatrecord-0.6.0.dist-info/entry_points.txt
whatrecord-0.6.0.dist-info/top_level.txt
whatrecord-0.6.0.dist-info/RECORD
