Metadata-Version: 2.1
Name: whatrecord
Version: 0.6.0
Summary: EPICS IOC record search and meta information tool
Author: SLAC National Accelerator Laboratory
License: Copyright (c) 2023, The Board of Trustees of the Leland Stanford Junior
Classifier: Development Status :: 5 - Production/Stable
Classifier: Natural Language :: English
Classifier: Programming Language :: Python :: 3
Requires-Python: >=3.9
License-File: LICENSE.md
License-File: AUTHORS.rst
Requires-Dist: aiohttp
Requires-Dist: apischema[graphql]
Requires-Dist: epicsmacrolib
Requires-Dist: graphviz <0.18
Requires-Dist: jinja2
Requires-Dist: lark
Provides-Extra: doc
Requires-Dist: mkdocs ; extra == 'doc'
Requires-Dist: mkdocs-autorefs ; extra == 'doc'
Requires-Dist: mkdocs-material ; extra == 'doc'
Requires-Dist: mkdocstrings[python] ; extra == 'doc'
Requires-Dist: pytkdocs[numpy-style] ; extra == 'doc'
Provides-Extra: test
Requires-Dist: codecov ; extra == 'test'
Requires-Dist: flake8 ; extra == 'test'
Requires-Dist: pytest ; extra == 'test'
Requires-Dist: pytest-asyncio ; extra == 'test'
Requires-Dist: pytest-cov ; extra == 'test'
Requires-Dist: blark ; extra == 'test'
Requires-Dist: happi ; extra == 'test'
Requires-Dist: python-ldap ; extra == 'test'
Requires-Dist: pytmc ; extra == 'test'
